ld_eventsource/__init__.py
ld_eventsource/actions.py
ld_eventsource/config/__init__.py
ld_eventsource/config/connect_strategy.py
ld_eventsource/config/error_strategy.py
ld_eventsource/config/retry_delay_strategy.py
ld_eventsource/errors.py
ld_eventsource/http.py
ld_eventsource/reader.py
ld_eventsource/sse_client.py
ld_eventsource/testing/__init__.py
ld_eventsource/testing/helpers.py
ld_eventsource/testing/http_util.py
ld_eventsource/testing/test_error_strategy.py
ld_eventsource/testing/test_http_connect_strategy.py
ld_eventsource/testing/test_http_connect_strategy_with_sse_client.py
ld_eventsource/testing/test_reader.py
ld_eventsource/testing/test_retry_delay_strategy.py
ld_eventsource/testing/test_sse_client_basic.py
ld_eventsource/testing/test_sse_client_retry.py
ld_eventsource/version.py
launchdarkly_eventsource-1.4.0.dist-info/METADATA
launchdarkly_eventsource-1.4.0.dist-info/WHEEL
launchdarkly_eventsource-1.4.0.dist-info/licenses/LICENSE
launchdarkly_eventsource-1.4.0.dist-info/RECORD
