Metadata-Version: 2.4
Name: launchdarkly-eventsource
Version: 1.4.0
Summary: LaunchDarkly SSE Client
License: Apache-2.0
License-File: LICENSE
Author: LaunchDarkly
Author-email: dev@launchdarkly.com
Requires-Python: >=3.9
Classifier: Intended Audience :: Developers
Classifier: License :: OSI Approved :: Apache Software License
Classifier: Operating System :: OS Independent
Classifier: Programming Language :: Python :: 3
Classifier: Programming Language :: Python :: 3.9
Classifier: Programming Language :: Python :: 3.10
Classifier: Programming Language :: Python :: 3.11
Classifier: Programming Language :: Python :: 3.12
Classifier: Programming Language :: Python :: 3.13
Classifier: Programming Language :: Python :: 3.14
Classifier: Topic :: Software Development
Classifier: Topic :: Software Development :: Libraries
Requires-Dist: urllib3 (>=1.26.0,<3)
Project-URL: Documentation, https://launchdarkly-python-sdk.readthedocs.io/en/latest/
Project-URL: Homepage, https://docs.launchdarkly.com/sdk/server-side/python
Project-URL: Repository, https://github.com/launchdarkly/python-eventsource
